omdrivers/CMC.py
omdrivers/Compellent.py
omdrivers/EqualLogic.py
omdrivers/F10.py
omdrivers/F10NG.py
omdrivers/FileList.py
omdrivers/MDArray.py
omdrivers/ME4.py
omdrivers/NGM.py
omdrivers/NSeries.py
omdrivers/Nagios.py
omdrivers/OME.py
omdrivers/Printer.py
omdrivers/__DellDrivers__.py
omdrivers/__init__.py
omdrivers/emcScaleIO.py
omdrivers/emcViper.py
omdrivers/iDRAC.py
omdrivers/CMC/CMC.Monitor
omdrivers/Compellent/Compellent.Monitor
omdrivers/EqualLogic/EqualLogic.Monitor
omdrivers/F10/F10.Monitor
omdrivers/F10/__init__.py
omdrivers/F10NG/F10NG.Monitor
omdrivers/F10NG/__init__.py
omdrivers/MDArray/MDArray.Monitor
omdrivers/ME4/ME4.Monitor
omdrivers/NGM/NGM.Monitor
omdrivers/NSeries/NSeries.Monitor
omdrivers/Printer/Printer.Monitor
omdrivers/enums/__init__.py
omdrivers/enums/iDRAC/BIOS.py
omdrivers/enums/iDRAC/FCHBA.py
omdrivers/enums/iDRAC/NIC.py
omdrivers/enums/iDRAC/PCIeSSD.py
omdrivers/enums/iDRAC/RAID.py
omdrivers/enums/iDRAC/__init__.py
omdrivers/enums/iDRAC/iDRAC.py
omdrivers/enums/iDRAC/iDRACEnums.py
omdrivers/helpers/__init__.py
omdrivers/helpers/iDRAC/CollectInventory.py
omdrivers/helpers/iDRAC/CompareInventory.py
omdrivers/helpers/iDRAC/RepoBuilder.py
omdrivers/helpers/iDRAC/UpdateHelper.py
omdrivers/helpers/iDRAC/__init__.py
omdrivers/iDRAC/iDRAC.Monitor
omdrivers/iDRAC/Config/BIOS.json
omdrivers/iDRAC/Config/EventFilters.json
omdrivers/iDRAC/Config/FCHBA.json
omdrivers/iDRAC/Config/Firmware.json
omdrivers/iDRAC/Config/NIC.json
omdrivers/iDRAC/Config/OS.json
omdrivers/iDRAC/Config/PCIeSSD.json
omdrivers/iDRAC/Config/RAID.json
omdrivers/iDRAC/Config/iDRAC.comp_spec
omdrivers/iDRAC/Config/iDRAC.json
omdrivers/lifecycle/__init__.py
omdrivers/lifecycle/F10/F10Config.py
omdrivers/lifecycle/F10/__init__.py
omdrivers/lifecycle/iDRAC/RAIDHelper.py
omdrivers/lifecycle/iDRAC/SCPParsers.py
omdrivers/lifecycle/iDRAC/__init__.py
omdrivers/lifecycle/iDRAC/iDRACConfig.py
omdrivers/lifecycle/iDRAC/iDRACCredsMgmt.py
omdrivers/lifecycle/iDRAC/iDRACJobs.py
omsdk-1.2.518.dist-info/LICENSE
omsdk-1.2.518.dist-info/METADATA
omsdk-1.2.518.dist-info/WHEEL
omsdk-1.2.518.dist-info/top_level.txt
omsdk-1.2.518.dist-info/RECORD
