Metadata-Version: 2.1
Name: omsdk
Version: 1.2.518
Summary: Dell OpenManage SDK
Home-page: https://support.dell.com
Author: Dell Technologies
Author-email: OpenManageSDK@Dell.com
License: Apache Software License
Keywords: dellemc,dellemcsdk,idrac,cmc
Platform: UNKNOWN
Classifier: Development Status :: 5 - Production/Stable
Classifier: Intended Audience :: Developers
Classifier: Topic :: Software Development :: Build Tools
Classifier: License :: OSI Approved :: Apache Software License
Classifier: Programming Language :: Python :: 2
Classifier: Programming Language :: Python :: 3
Requires-Dist: requests (>=2.12.3)
Requires-Dist: PyYAML (>=3.12)
Requires-Dist: future (>=0.16.0)
Requires-Dist: pysnmp-mibs (>=0)
Requires-Dist: ipaddress (>=0)
Requires-Dist: enum34 ; python_version < "3.4"
